django_saml2_auth/__init__.py
django_saml2_auth/urls.py
django_saml2_auth/views.py
django_saml2_auth/templates/django_saml2_auth/denied.html
django_saml2_auth/templates/django_saml2_auth/signout.html
django_saml2_auth_custom/__init__.py
django_saml2_auth_custom/urls.py
django_saml2_auth_custom/views.py
django_saml2_auth_custom/templates/django_saml2_auth_custom/denied.html
django_saml2_auth_custom/templates/django_saml2_auth_custom/signout.html
django_saml2_auth_custom-1.0.4.dist-info/AUTHORS.rst
django_saml2_auth_custom-1.0.4.dist-info/LICENSE
django_saml2_auth_custom-1.0.4.dist-info/METADATA
django_saml2_auth_custom-1.0.4.dist-info/WHEEL
django_saml2_auth_custom-1.0.4.dist-info/top_level.txt
django_saml2_auth_custom-1.0.4.dist-info/RECORD
