Metadata-Version: 2.1
Name: django-saml2-auth-custom
Version: 1.0.4
Summary: CUSTOM Django SAML2 Authentication
Home-page: https://github.com/fangli/django-saml2-auth
Author: Fang Li
Author-email: surivlee+djsaml2auth@gmail.com
License: Apache 2.0
Keywords: CUSTOM Django SAML2 Authentication
Platform: UNKNOWN
Classifier: Development Status :: 5 - Production/Stable
Classifier: Intended Audience :: Developers
Classifier: Topic :: Software Development :: Libraries :: Python Modules
Classifier: License :: OSI Approved :: Apache Software License
Classifier: Framework :: Django :: 1.5
Classifier: Framework :: Django :: 1.6
Classifier: Framework :: Django :: 1.7
Classifier: Framework :: Django :: 1.8
Classifier: Framework :: Django :: 1.9
Classifier: Programming Language :: Python :: 2
Classifier: Programming Language :: Python :: 2.6
Classifier: Programming Language :: Python :: 2.7
Classifier: Programming Language :: Python :: 3
Classifier: Programming Language :: Python :: 3.3
Classifier: Programming Language :: Python :: 3.4
Classifier: Programming Language :: Python :: 3.5
Requires-Dist: pysaml2 (==4.0.5)
